_rtpsynth.cpython-313-aarch64-linux-gnu.so
rtpsynth/RtpJBuf.py
rtpsynth/RtpSynth.py
rtpsynth/__init__.py
rtpsynth/env.py
rtpsynth-1.2.1.dist-info/METADATA
rtpsynth-1.2.1.dist-info/WHEEL
rtpsynth-1.2.1.dist-info/top_level.txt
rtpsynth-1.2.1.dist-info/RECORD
rtpsynth-1.2.1.dist-info/licenses/LICENSE
