Metadata-Version: 2.1
Name: rtpsynth
Version: 1.2.1
Summary: Library optimized to generate/process sequence of the RTP packets
Home-page: https://github.com/sippy/librtpsynth.git
Author: Maksym Sobolyev
Author-email: sobomax@gmail.com
License: BSD-2-Clause
Classifier: Operating System :: POSIX
Classifier: Programming Language :: C
Classifier: Programming Language :: Python
License-File: LICENSE
